reversestem/__init__.py
reversestem/dmo/__init__.py
reversestem/dmo/helper_functions.py
reversestem/dto/__init__.py
reversestem/dto/a/__init__.py
reversestem/dto/a/finder_a.py
reversestem/dto/a/stem_a_.py
reversestem/dto/a/stem_aa.py
reversestem/dto/a/stem_ab.py
reversestem/dto/a/stem_ac.py
reversestem/dto/a/stem_ad.py
reversestem/dto/a/stem_ae.py
reversestem/dto/a/stem_af.py
reversestem/dto/a/stem_ag.py
reversestem/dto/a/stem_ah.py
reversestem/dto/a/stem_ai.py
reversestem/dto/a/stem_aj.py
reversestem/dto/a/stem_ak.py
reversestem/dto/a/stem_al.py
reversestem/dto/a/stem_am.py
reversestem/dto/a/stem_an.py
reversestem/dto/a/stem_ao.py
reversestem/dto/a/stem_ap.py
reversestem/dto/a/stem_aq.py
reversestem/dto/a/stem_ar.py
reversestem/dto/a/stem_as.py
reversestem/dto/a/stem_at.py
reversestem/dto/a/stem_au.py
reversestem/dto/a/stem_av.py
reversestem/dto/a/stem_aw.py
reversestem/dto/a/stem_ay.py
reversestem/dto/a/stem_az.py
reversestem/dto/b/__init__.py
reversestem/dto/b/finder_b.py
reversestem/dto/b/stem_b_.py
reversestem/dto/b/stem_ba.py
reversestem/dto/b/stem_bb.py
reversestem/dto/b/stem_bc.py
reversestem/dto/b/stem_bd.py
reversestem/dto/b/stem_be.py
reversestem/dto/b/stem_bf.py
reversestem/dto/b/stem_bg.py
reversestem/dto/b/stem_bh.py
reversestem/dto/b/stem_bi.py
reversestem/dto/b/stem_bj.py
reversestem/dto/b/stem_bk.py
reversestem/dto/b/stem_bl.py
reversestem/dto/b/stem_bm.py
reversestem/dto/b/stem_bn.py
reversestem/dto/b/stem_bo.py
reversestem/dto/b/stem_bp.py
reversestem/dto/b/stem_bq.py
reversestem/dto/b/stem_br.py
reversestem/dto/b/stem_bs.py
reversestem/dto/b/stem_bt.py
reversestem/dto/b/stem_bu.py
reversestem/dto/b/stem_bv.py
reversestem/dto/b/stem_bw.py
reversestem/dto/b/stem_by.py
reversestem/dto/b/stem_bz.py
reversestem/dto/c/__init__.py
reversestem/dto/c/finder_c.py
reversestem/dto/c/stem_c_.py
reversestem/dto/c/stem_ca.py
reversestem/dto/c/stem_cb.py
reversestem/dto/c/stem_cc.py
reversestem/dto/c/stem_cd.py
reversestem/dto/c/stem_ce.py
reversestem-0.1.2.dist-info/WHEEL
reversestem-0.1.2.dist-info/METADATA
reversestem-0.1.2.dist-info/RECORD
