Metadata-Version: 2.1
Name: reversestem
Version: 0.1.2
Summary: Unigram Lexicon for Reverse Stem Lookups
Home-page: https://github.com/craigtrim/reversestem
License: None
Keywords: nlp,nlu,stem,porter,stemmer
Author: Craig Trim
Author-email: craigtrim@gmail.com
Maintainer: Craig Trim
Maintainer-email: craigtrim@gmail.com
Requires-Python: >=3.8.5,<4.0.0
Classifier: Development Status :: 4 - Beta
Classifier: License :: Other/Proprietary License
Classifier: Programming Language :: Python :: 3
Classifier: Programming Language :: Python :: 3.10
Classifier: Programming Language :: Python :: 3.9
Classifier: Topic :: Scientific/Engineering :: Artificial Intelligence
Classifier: Topic :: Software Development :: Libraries :: Python Modules
Requires-Dist: baseblock
Requires-Dist: unicodedata2
Project-URL: Bug Tracker, https://github.com/craigtrim/reversestem/issues
Project-URL: Repository, https://github.com/craigtrim/reversestem
